table2latex/__init__.py
table2latex/table2latex.py
Table2Tex-0.0.1.dist-info/LICENSE
Table2Tex-0.0.1.dist-info/METADATA
Table2Tex-0.0.1.dist-info/WHEEL
Table2Tex-0.0.1.dist-info/top_level.txt
Table2Tex-0.0.1.dist-info/RECORD
