Metadata-Version: 2.1
Name: Table2Tex
Version: 0.0.1
Summary: Improvement on
Home-page: https://github.com/Tesla2000/Table2Latex
Author: Tesla2000
Author-email: fratajczak124@gmail.com
Project-URL: Homepage, https://github.com/Tesla2000/Table2Latex
Classifier: Programming Language :: Python :: 3
Classifier: License :: OSI Approved :: MIT License
Classifier: Operating System :: OS Independent
Requires-Python: >=3.5
License-File: LICENSE
